flashscenic/__init__.py
flashscenic/aucell.py
flashscenic-0.0.1.dist-info/licenses/LICENSE
flashscenic-0.0.1.dist-info/WHEEL
flashscenic-0.0.1.dist-info/METADATA
flashscenic-0.0.1.dist-info/RECORD
