Metadata-Version: 2.4
Name: flashscenic
Version: 0.0.1
Summary: GPU based SCENIC analysis with RegDiffusion and accelerated AUCell analysis
Author-email: Hao Zhu <haozhu233@gmail.com>, Donna Slonim <donna.slonim@tufts.edu>
Maintainer-email: Hao Zhu <haozhu233@gmail.com>
License-Expression: MIT
License-File: LICENSE
Requires-Dist: numpy>=1.16.5
Requires-Dist: torch
Project-URL: Home, https://github.com/haozhu233/flashscenic
